grizpy/__init__.py
grizpy-0.1.dist-info/DESCRIPTION.rst
grizpy-0.1.dist-info/METADATA
grizpy-0.1.dist-info/RECORD
grizpy-0.1.dist-info/WHEEL
grizpy-0.1.dist-info/metadata.json
grizpy-0.1.dist-info/top_level.txt
