Metadata-Version: 2.0
Name: grizpy
Version: 0.1
Summary: The funniest joke in the world
Home-page: http://github.com/storborg/funniest
Author: Mahmoud Alfayoumi
Author-email: mah.fay.g@gmail.com
License: UNKNOWN
Platform: UNKNOWN
